scopedlog/__init__.py
scopedlog/idgen_seq.py
scopedlog/idgen_uuid.py
scopedlog/sink_structlog.py
scopedlog-0.1.4.dist-info/DESCRIPTION.rst
scopedlog-0.1.4.dist-info/METADATA
scopedlog-0.1.4.dist-info/RECORD
scopedlog-0.1.4.dist-info/WHEEL
scopedlog-0.1.4.dist-info/metadata.json
scopedlog-0.1.4.dist-info/top_level.txt
