Metadata-Version: 2.0
Name: scopedlog
Version: 0.1.4
Summary: library for scoped logging on top of structlog (or similar sinks)
Home-page: https://github.com/kshpytsya/scopedlog
Author: Kyrylo Shpytsya
Author-email: kshpitsa@gmail.com
License: MIT
Platform: UNKNOWN
Classifier: Development Status :: 4 - Beta
Classifier: Intended Audience :: Developers
Classifier: License :: OSI Approved :: MIT License
Classifier: Programming Language :: Python :: 3.6
Classifier: Programming Language :: Python :: 3.7
Requires-Python: >=3.6, <=3.7
Provides-Extra: structlog
Provides-Extra: structlog
Requires-Dist: structlog (<19,>=18.1.0); extra == 'structlog'
